Workbook

Sheet 1.CLV CalcuLation
A1: CUSTUMER_ID | B1: Purchases Per Custumer | C1: Total revenue(List_prie) | D1: Average of Custumer Lifespan(tenure) | E1: CLV | F1: job_industry_category | G1: WEALTH SEGMENT
A2: 1 | B2: 11 | C2: 9084.45 | D2: 11 | E2: =B2*C2*D2 -> 1099218.4 | F2: =VLOOKUP('1.CLV CalcuLation'!A2,Customer_Demographic__2[],8,FALSE) -> Health | G2: =VLOOKUP(A2,Customer_Demographic__2[#All],9,FALSE) -> Mass Customer
A3: 2 | B3: 3 | C3: 4149.07 | D3: 16 | E3: =B3*C3*D3 -> 199155.36 | F3: =VLOOKUP('1.CLV CalcuLation'!A3,Customer_Demographic__2[],8,FALSE) -> Financial Services | G3: =VLOOKUP(A3,Customer_Demographic__2[#All],9,FALSE) -> Mass Customer
A4: 3 | B4: 7 | C4: 9525.22 | D4: 15 | E4: =B4*C4*D4 -> 1000148.1 | F4: =VLOOKUP('1.CLV CalcuLation'!A4,Customer_Demographic__2[],8,FALSE) -> Property | G4: =VLOOKUP(A4,Customer_Demographic__2[#All],9,FALSE) -> Mass Customer
A5: 4 | B5: 2 | C5: 1047.72 | D5: 7 | E5: =B5*C5*D5 -> 14668.08 | F5: =VLOOKUP('1.CLV CalcuLation'!A5,Customer_Demographic__2[],8,FALSE) -> IT | G5: =VLOOKUP(A5,Customer_Demographic__2[#All],9,FALSE) -> Mass Customer
A6: 5 | B6: 6 | C6: 5903.2 | D6: 8 | E6: =B6*C6*D6 -> 283353.6 | F6: =VLOOKUP('1.CLV CalcuLation'!A6,Customer_Demographic__2[],8,FALSE) -> Others | G6: =VLOOKUP(A6,Customer_Demographic__2[#All],9,FALSE) -> Affluent Customer
A7: 6 | B7: 5 | C7: 5931.69 | D7: 13 | E7: =B7*C7*D7 -> 385559.85 | F7: =VLOOKUP('1.CLV CalcuLation'!A7,Customer_Demographic__2[],8,FALSE) -> Retail | G7: =VLOOKUP(A7,Customer_Demographic__2[#All],9,FALSE) -> High Net Worth
A8: 7 | B8: 3 | C8: 995.38 | D8: 11 | E8: =B8*C8*D8 -> 32847.54 | F8: =VLOOKUP('1.CLV CalcuLation'!A8,Customer_Demographic__2[],8,FALSE) -> Financial Services | G8: =VLOOKUP(A8,Customer_Demographic__2[#All],9,FALSE) -> Affluent Customer
A9: 8 | B9: 9 | C9: 9933.29 | D9: 7 | E9: =B9*C9*D9 -> 625797.27 | F9: =VLOOKUP('1.CLV CalcuLation'!A9,Customer_Demographic__2[],8,FALSE) -> Others | G9: =VLOOKUP(A9,Customer_Demographic__2[#All],9,FALSE) -> Mass Customer
A10: 9 | B10: 6 | C10: 5357.55 | D10: 8 | E10: =B10*C10*D10 -> 257162.4 | F10: =VLOOKUP('1.CLV CalcuLation'!A10,Customer_Demographic__2[],8,FALSE) -> Argiculture | G10: =VLOOKUP(A10,Customer_Demographic__2[#All],9,FALSE) -> Affluent Customer
A11: 10 | B11: 5 | C11: 5003.75 | D11: 20 | E11: =B11*C11*D11 -> 500375 | F11: =VLOOKUP('1.CLV CalcuLation'!A11,Customer_Demographic__2[],8,FALSE) -> Financial Services | G11: =VLOOKUP(A11,Customer_Demographic__2[#All],9,FALSE) -> Mass Customer
A12: 11 | B12: 5 | C12: 6026.8 | D12: 9 | E12: =B12*C12*D12 -> 271206 | F12: =VLOOKUP('1.CLV CalcuLation'!A12,Customer_Demographic__2[],8,FALSE) -> Property | G12: =VLOOKUP(A12,Customer_Demographic__2[#All],9,FALSE) -> Mass Customer
A13: 12 | B13: 7 | C13: 6394.21 | D13: 8 | E13: =B13*C13*D13 -> 358075.76 | F13: =VLOOKUP('1.CLV CalcuLation'!A13,Customer_Demographic__2[],8,FALSE) -> Manufacturing | G13: =VLOOKUP(A13,Customer_Demographic__2[#All],9,FALSE) -> Mass Customer
... A144: 143 | B144: 4 | C144: 4689.21 | D144: 11 | E144: =B144*C144*D144 -> 206325.24 | F144: =VLOOKUP('1.CLV CalcuLation'!A144,Customer_Demographic__2[],8,FALSE) -> Argiculture | G144: =VLOOKUP(A144,Customer_Demographic__2[#All],9,FALSE) -> Mass Customer
A145: 144 | B145: 8 | C145: 8961.14 | E145: =B145*C145*D145 -> 0 | F145: =VLOOKUP('1.CLV CalcuLation'!A145,Customer_Demographic__2[],8,FALSE) -> IT | G145: =VLOOKUP(A145,Customer_Demographic__2[#All],9,FALSE) -> Mass Customer
A146: 145 | B146: 7 | C146: 8149.19 | D146: 4 | E146: =B146*C146*D146 -> 228177.32 | F146: =VLOOKUP('1.CLV CalcuLation'!A146,Customer_Demographic__2[],8,FALSE) -> Financial Services | G146: =VLOOKUP(A146,Customer_Demographic__2[#All],9,FALSE) -> Mass Customer
A147: 146 | B147: 2 | C147: 1973.29 | D147: 8 | E147: =B147*C147*D147 -> 31572.64 | F147: =VLOOKUP('1.CLV CalcuLation'!A147,Customer_Demographic__2[],8,FALSE) -> Manufacturing | G147: =VLOOKUP(A147,Customer_Demographic__2[#All],9,FALSE) -> Mass Customer
A148: 147 | B148: 6 | C148: 8079.09 | D148: 10 | E148: =B148*C148*D148 -> 484745.4 | F148: =VLOOKUP('1.CLV CalcuLation'!A148,Customer_Demographic__2[],8,FALSE) -> Health | G148: =VLOOKUP(A148,Customer_Demographic__2[#All],9,FALSE) -> Mass Customer
A149: 148 | B149: 5 | C149: 5808.83 | D149: 5 | E149: =B149*C149*D149 -> 145220.75 | F149: =VLOOKUP('1.CLV CalcuLation'!A149,Customer_Demographic__2[],8,FALSE) -> Others | G149: =VLOOKUP(A149,Customer_Demographic__2[#All],9,FALSE) -> Mass Customer
A150: 149 | B150: 4 | C150: 4945.69 | D150: 1 | E150: =B150*C150*D150 -> 19782.76 | F150: =VLOOKUP('1.CLV CalcuLation'!A150,Customer_Demographic__2[],8,FALSE) -> Health | G150: =VLOOKUP(A150,Customer_Demographic__2[#All],9,FALSE) -> Mass Customer
A151: 150 | B151: 4 | C151: 3630.96 | D151: 17 | E151: =B151*C151*D151 -> 246905.28 | F151: =VLOOKUP('1.CLV CalcuLation'!A151,Customer_Demographic__2[],8,FALSE) -> Financial Services | G151: =VLOOKUP(A151,Customer_Demographic__2[#All],9,FALSE) -> Affluent Customer
A152: 151 | B152: 7 | C152: 11422.85 | D152: 13 | E152: =B152*C152*D152 -> 1039479.3 | F152: =VLOOKUP('1.CLV CalcuLation'!A152,Customer_Demographic__2[],8,FALSE) -> Manufacturing | G152: =VLOOKUP(A152,Customer_Demographic__2[#All],9,FALSE) -> Mass Customer
A153: 152 | B153: 2 | C153: 2941.37 | D153: 16 | E153: =B153*C153*D153 -> 94123.84 | F153: =VLOOKUP('1.CLV CalcuLation'!A153,Customer_Demographic__2[],8,FALSE) -> Financial Services | G153: =VLOOKUP(A153,Customer_Demographic__2[#All],9,FALSE) -> Mass Customer
A154: 153 | B154: 7 | C154: 7808.16 | D154: 12 | E154: =B154*C154*D154 -> 655885.44 | F154: =VLOOKUP('1.CLV CalcuLation'!A154,Customer_Demographic__2[],8,FALSE) -> Entertainment | G154: =VLOOKUP(A154,Customer_Demographic__2[#All],9,FALSE) -> Mass Customer
A155: 154 | B155: 5 | C155: 3521.53 | D155: 11 | E155: =B155*C155*D155 -> 193684.15 | F155: =VLOOKUP('1.CLV CalcuLation'!A155,Customer_Demographic__2[],8,FALSE) -> Others | G155: =VLOOKUP(A155,Customer_Demographic__2[#All],9,FALSE) -> Mass Customer
A156: 155 | B156: 3 | C156: 4008.51 | D156: 10 | E156: =B156*C156*D156 -> 120255.3 | F156: =VLOOKUP('1.CLV CalcuLation'!A156,Customer_Demographic__2[],8,FALSE) -> Manufacturing | G156: =VLOOKUP(A156,Customer_Demographic__2[#All],9,FALSE) -> Mass Customer
A157: 156 | B157: 5 | C157: 4831.58 | D157: 11 | E157: =B157*C157*D157 -> 265736.9 | F157: =VLOOKUP('1.CLV CalcuLation'!A157,Customer_Demographic__2[],8,FALSE) -> Financial Services | G157: =VLOOKUP(A157,Customer_Demographic__2[#All],9,FALSE) -> Mass Customer
... A168: 167 | B168: 9 | C168: 9888.61 | D168: 17 | E168: =B168*C168*D168 -> 1512957.3 | F168: =VLOOKUP('1.CLV CalcuLation'!A168,Customer_Demographic__2[],8,FALSE) -> Health | G168: =VLOOKUP(A168,Customer_Demographic__2[#All],9,FALSE) -> High Net Worth
A169: 168 | B169: 8 | C169: 8563.42 | E169: =B169*C169*D169 -> 0 | F169: =VLOOKUP('1.CLV CalcuLation'!A169,Customer_Demographic__2[],8,FALSE) -> IT | G169: =VLOOKUP(A169,Customer_Demographic__2[#All],9,FALSE) -> Affluent Customer
A170: 169 | B170: 3 | C170: 2065.08 | D170: 5 | E170: =B170*C170*D170 -> 30976.2 | F170: =VLOOKUP('1.CLV CalcuLation'!A170,Customer_Demographic__2[],8,FALSE) -> Telecommunications | G170: =VLOOKUP(A170,Customer_Demographic__2[#All],9,FALSE) -> High Net Worth
A171: 170 | B171: 3 | C171: 3684.75 | D171: 21 | E171: =B171*C171*D171 -> 232139.25 | F171: =VLOOKUP('1.CLV CalcuLation'!A171,Customer_Demographic__2[],8,FALSE) -> Health | G171: =VLOOKUP(A171,Customer_Demographic__2[#All],9,FALSE) -> High Net Worth
A172: 171 | B172: 8 | C172: 9347.85 | D172: 10 | E172: =B172*C172*D172 -> 747828 | F172: =VLOOKUP('1.CLV CalcuLation'!A172,Customer_Demographic__2[],8,FALSE) -> Manufacturing | G172: =VLOOKUP(A172,Customer_Demographic__2[#All],9,FALSE) -> Mass Customer
A173: 172 | B173: 7 | C173: 9250.22 | D173: 6 | E173: =B173*C173*D173 -> 388509.24 | F173: =VLOOKUP('1.CLV CalcuLation'!A173,Customer_Demographic__2[],8,FALSE) -> Manufacturing | G173: =VLOOKUP(A173,Customer_Demographic__2[#All],9,FALSE) -> Affluent Customer
A174: 173 | B174: 9 | C174: 14061.48 | D174: 1 | E174: =B174*C174*D174 -> 126553.32 | F174: =VLOOKUP('1.CLV CalcuLation'!A174,Customer_Demographic__2[],8,FALSE) -> Health | G174: =VLOOKUP(A174,Customer_Demographic__2[#All],9,FALSE) -> Affluent Customer
A175: 174 | B175: 10 | C175: 12893.57 | D175: 12 | E175: =B175*C175*D175 -> 1547228.4 | F175: =VLOOKUP('1.CLV CalcuLation'!A175,Customer_Demographic__2[],8,FALSE) -> Health | G175: =VLOOKUP(A175,Customer_Demographic__2[#All],9,FALSE) -> Mass Customer
A176: 175 | B176: 5 | C176: 6008.03 | D176: 5 | E176: =B176*C176*D176 -> 150200.75 | F176: =VLOOKUP('1.CLV CalcuLation'!A176,Customer_Demographic__2[],8,FALSE) -> Manufacturing | G176: =VLOOKUP(A176,Customer_Demographic__2[#All],9,FALSE) -> Affluent Customer
A177: 176 | B177: 4 | C177: 6146.7 | D177: 10 | E177: =B177*C177*D177 -> 245868 | F177: =VLOOKUP('1.CLV CalcuLation'!A177,Customer_Demographic__2[],8,FALSE) -> Property | G177: =VLOOKUP(A177,Customer_Demographic__2[#All],9,FALSE) -> Mass Customer
A178: 177 | B178: 12 | C178: 11826.34 | D178: 4 | E178: =B178*C178*D178 -> 567664.32 | F178: =VLOOKUP('1.CLV CalcuLation'!A178,Customer_Demographic__2[],8,FALSE) -> Financial Services | G178: =VLOOKUP(A178,Customer_Demographic__2[#All],9,FALSE) -> High Net Worth
A179: 178 | B179: 4 | C179: 3504.09 | D179: 8 | E179: =B179*C179*D179 -> 112130.88 | F179: =VLOOKUP('1.CLV CalcuLation'!A179,Customer_Demographic__2[],8,FALSE) -> Others | G179: =VLOOKUP(A179,Customer_Demographic__2[#All],9,FALSE) -> Affluent Customer
A180: 179 | B180: 3 | C180: 3168.84 | D180: 6 | E180: =B180*C180*D180 -> 57039.12 | F180: =VLOOKUP('1.CLV CalcuLation'!A180,Customer_Demographic__2[],8,FALSE) -> Manufacturing | G180: =VLOOKUP(A180,Customer_Demographic__2[#All],9,FALSE) -> High Net Worth
A181: 180 | B181: 7 | C181: 7970.57 | D181: 14 | E181: =B181*C181*D181 -> 781115.86 | F181: =VLOOKUP('1.CLV CalcuLation'!A181,Customer_Demographic__2[],8,FALSE) -> Argiculture | G181: =VLOOKUP(A181,Customer_Demographic__2[#All],9,FALSE) -> Affluent Customer
... A267: 266 | B267: 4 | C267: 4191.43 | D267: 18 | E267: =B267*C267*D267 -> 301782.96 | F267: =VLOOKUP('1.CLV CalcuLation'!A267,Customer_Demographic__2[],8,FALSE) -> Retail | G267: =VLOOKUP(A267,Customer_Demographic__2[#All],9,FALSE) -> Affluent Customer
A268: 267 | B268: 4 | C268: 5029.25 | E268: =B268*C268*D268 -> 0 | F268: =VLOOKUP('1.CLV CalcuLation'!A268,Customer_Demographic__2[],8,FALSE) -> IT | G268: =VLOOKUP(A268,Customer_Demographic__2[#All],9,FALSE) -> High Net Worth
A269: 268 | B269: 4 | C269: 5104.56 | D269: 10 | E269: =B269*C269*D269 -> 204182.4 | F269: =VLOOKUP('1.CLV CalcuLation'!A269,Customer_Demographic__2[],8,FALSE) -> Manufacturing | G269: =VLOOKUP(A269,Customer_Demographic__2[#All],9,FALSE) -> Mass Customer
A270: 269 | B270: 5 | C270: 5215.37 | D270: 9 | E270: =B270*C270*D270 -> 234691.65 | F270: =VLOOKUP('1.CLV CalcuLation'!A270,Customer_Demographic__2[],8,FALSE) -> Property | G270: =VLOOKUP(A270,Customer_Demographic__2[#All],9,FALSE) -> Mass Customer
A271: 270 | B271: 7 | C271: 7413.61 | D271: 17 | E271: =B271*C271*D271 -> 882219.59 | F271: =VLOOKUP('1.CLV CalcuLation'!A271,Customer_Demographic__2[],8,FALSE) -> Others | G271: =VLOOKUP(A271,Customer_Demographic__2[#All],9,FALSE) -> Mass Customer
A272: 271 | B272: 2 | C272: 2293.02 | D272: 4 | E272: =B272*C272*D272 -> 18344.16 | F272: =VLOOKUP('1.CLV CalcuLation'!A272,Customer_Demographic__2[],8,FALSE) -> Financial Services | G272: =VLOOKUP(A272,Customer_Demographic__2[#All],9,FALSE) -> Mass Customer
A273: 272 | B273: 7 | C273: 7345.17 | D273: 1 | E273: =B273*C273*D273 -> 51416.19 | F273: =VLOOKUP('1.CLV CalcuLation'!A273,Customer_Demographic__2[],8,FALSE) -> Retail | G273: =VLOOKUP(A273,Customer_Demographic__2[#All],9,FALSE) -> Mass Customer
A274: 273 | B274: 10 | C274: 11372.24 | D274: 19 | E274: =B274*C274*D274 -> 2160725.6 | F274: =VLOOKUP('1.CLV CalcuLation'!A274,Customer_Demographic__2[],8,FALSE) -> Others | G274: =VLOOKUP(A274,Customer_Demographic__2[#All],9,FALSE) -> Mass Customer
A275: 274 | B275: 4 | C275: 2597.68 | D275: 14 | E275: =B275*C275*D275 -> 145470.08 | F275: =VLOOKUP('1.CLV CalcuLation'!A275,Customer_Demographic__2[],8,FALSE) -> Health | G275: =VLOOKUP(A275,Customer_Demographic__2[#All],9,FALSE) -> Mass Customer
A276: 275 | B276: 6 | C276: 8841.83 | D276: 13 | E276: =B276*C276*D276 -> 689662.74 | F276: =VLOOKUP('1.CLV CalcuLation'!A276,Customer_Demographic__2[],8,FALSE) -> Health | G276: =VLOOKUP(A276,Customer_Demographic__2[#All],9,FALSE) -> High Net Worth
A277: 276 | B277: 6 | C277: 6112.08 | D277: 22 | E277: =B277*C277*D277 -> 806794.56 | F277: =VLOOKUP('1.CLV CalcuLation'!A277,Customer_Demographic__2[],8,FALSE) -> Financial Services | G277: =VLOOKUP(A277,Customer_Demographic__2[#All],9,FALSE) -> Mass Customer
A278: 277 | B278: 3 | C278: 3580.48 | D278: 15 | E278: =B278*C278*D278 -> 161121.6 | F278: =VLOOKUP('1.CLV CalcuLation'!A278,Customer_Demographic__2[],8,FALSE) -> Others | G278: =VLOOKUP(A278,Customer_Demographic__2[#All],9,FALSE) -> High Net Worth
A279: 278 | B279: 1 | C279: 1228.07 | D279: 4 | E279: =B279*C279*D279 -> 4912.28 | F279: =VLOOKUP('1.CLV CalcuLation'!A279,Customer_Demographic__2[],8,FALSE) -> Others | G279: =VLOOKUP(A279,Customer_Demographic__2[#All],9,FALSE) -> Affluent Customer
A280: 279 | B280: 6 | C280: 3817.17 | D280: 11 | E280: =B280*C280*D280 -> 251933.22 | F280: =VLOOKUP('1.CLV CalcuLation'!A280,Customer_Demographic__2[],8,FALSE) -> Manufacturing | G280: =VLOOKUP(A280,Customer_Demographic__2[#All],9,FALSE) -> Mass Customer
... A290: 289 | B290: 9 | C290: 9320.12 | D290: 10 | E290: =B290*C290*D290 -> 838810.8 | F290: =VLOOKUP('1.CLV CalcuLation'!A290,Customer_Demographic__2[],8,FALSE) -> Health | G290: =VLOOKUP(A290,Customer_Demographic__2[#All],9,FALSE) -> High Net Worth
A291: 290 | B291: 5 | C291: 5912.93 | E291: =B291*C291*D291 -> 0 | F291: =VLOOKUP('1.CLV CalcuLation'!A291,Customer_Demographic__2[],8,FALSE) -> IT | G291: =VLOOKUP(A291,Customer_Demographic__2[#All],9,FALSE) -> Mass Customer
A292: 291 | B292: 2 | C292: 983.55 | D292: 4 | E292: =B292*C292*D292 -> 7868.4 | F292: =VLOOKUP('1.CLV CalcuLation'!A292,Customer_Demographic__2[],8,FALSE) -> Entertainment | G292: =VLOOKUP(A292,Customer_Demographic__2[#All],9,FALSE) -> Mass Customer
A293: 292 | B293: 7 | C293: 8825.97 | D293: 9 | E293: =B293*C293*D293 -> 556036.11 | F293: =VLOOKUP('1.CLV CalcuLation'!A293,Customer_Demographic__2[],8,FALSE) -> Others | G293: =VLOOKUP(A293,Customer_Demographic__2[#All],9,FALSE) -> Affluent Customer
A294: 293 | B294: 5 | C294: 5175.56 | D294: 20 | E294: =B294*C294*D294 -> 517556 | F294: =VLOOKUP('1.CLV CalcuLation'!A294,Customer_Demographic__2[],8,FALSE) -> Manufacturing | G294: =VLOOKUP(A294,Customer_Demographic__2[#All],9,FALSE) -> Mass Customer
A295: 294 | B295: 7 | C295: 8719.14 | D295: 5 | E295: =B295*C295*D295 -> 305169.9 | F295: =VLOOKUP('1.CLV CalcuLation'!A295,Customer_Demographic__2[],8,FALSE) -> Others | G295: =VLOOKUP(A295,Customer_Demographic__2[#All],9,FALSE) -> High Net Worth
A296: 295 | B296: 7 | C296: 5956.46 | D296: 18 | E296: =B296*C296*D296 -> 750513.96 | F296: =VLOOKUP('1.CLV CalcuLation'!A296,Customer_Demographic__2[],8,FALSE) -> Others | G296: =VLOOKUP(A296,Customer_Demographic__2[#All],9,FALSE) -> Mass Customer
A297: 296 | B297: 3 | C297: 4016.36 | D297: 17 | E297: =B297*C297*D297 -> 204834.36 | F297: =VLOOKUP('1.CLV CalcuLation'!A297,Customer_Demographic__2[],8,FALSE) -> Health | G297: =VLOOKUP(A297,Customer_Demographic__2[#All],9,FALSE) -> High Net Worth
A298: 297 | B298: 4 | C298: 5674.71 | D298: 16 | E298: =B298*C298*D298 -> 363181.44 | F298: =VLOOKUP('1.CLV CalcuLation'!A298,Customer_Demographic__2[],8,FALSE) -> Manufacturing | G298: =VLOOKUP(A298,Customer_Demographic__2[#All],9,FALSE) -> High Net Worth
A299: 298 | B299: 9 | C299: 10336.31 | D299: 9 | E299: =B299*C299*D299 -> 837241.11 | F299: =VLOOKUP('1.CLV CalcuLation'!A299,Customer_Demographic__2[],8,FALSE) -> Manufacturing | G299: =VLOOKUP(A299,Customer_Demographic__2[#All],9,FALSE) -> High Net Worth
A300: 299 | B300: 7 | C300: 10296.12 | D300: 7 | E300: =B300*C300*D300 -> 504509.88 | F300: =VLOOKUP('1.CLV CalcuLation'!A300,Customer_Demographic__2[],8,FALSE) -> Financial Services | G300: =VLOOKUP(A300,Customer_Demographic__2[#All],9,FALSE) -> Mass Customer
A301: 300 | B301: 5 | C301: 7003.74 | D301: 9 | E301: =B301*C301*D301 -> 315168.3 | F301: =VLOOKUP('1.CLV CalcuLation'!A301,Customer_Demographic__2[],8,FALSE) -> Health | G301: =VLOOKUP(A301,Customer_Demographic__2[#All],9,FALSE) -> Mass Customer
A302: 301 | B302: 2 | C302: 361.78 | D302: 19 | E302: =B302*C302*D302 -> 13747.64 | F302: =VLOOKUP('1.CLV CalcuLation'!A302,Customer_Demographic__2[],8,FALSE) -> Manufacturing | G302: =VLOOKUP(A302,Customer_Demographic__2[#All],9,FALSE) -> High Net Worth
A303: 302 | B303: 1 | C303: 1661.92 | D303: 13 | E303: =B303*C303*D303 -> 21604.96 | F303: =VLOOKUP('1.CLV CalcuLation'!A303,Customer_Demographic__2[],8,FALSE) -> Health | G303: =VLOOKUP(A303,Customer_Demographic__2[#All],9,FALSE) -> Mass Customer
... A451: 450 | B451: 4 | C451: 5369.55 | D451: 18 | E451: =B451*C451*D451 -> 386607.6 | F451: =VLOOKUP('1.CLV CalcuLation'!A451,Customer_Demographic__2[],8,FALSE) -> Entertainment | G451: =VLOOKUP(A451,Customer_Demographic__2[#All],9,FALSE) -> Mass Customer
A452: 451 | B452: 6 | C452: 5925.52 | E452: =B452*C452*D452 -> 0 | F452: =VLOOKUP('1.CLV CalcuLation'!A452,Customer_Demographic__2[],8,FALSE) -> IT | G452: =VLOOKUP(A452,Customer_Demographic__2[#All],9,FALSE) -> High Net Worth
A453: 452 | B453: 5 | C453: 3872.43 | D453: 5 | E453: =B453*C453*D453 -> 96810.75 | F453: =VLOOKUP('1.CLV CalcuLation'!A453,Customer_Demographic__2[],8,FALSE) -> Property | G453: =VLOOKUP(A453,Customer_Demographic__2[#All],9,FALSE) -> Mass Customer
A454: 453 | B454: 8 | C454: 6220.21 | E454: =B454*C454*D454 -> 0 | F454: =VLOOKUP('1.CLV CalcuLation'!A454,Customer_Demographic__2[],8,FALSE) -> IT | G454: =VLOOKUP(A454,Customer_Demographic__2[#All],9,FALSE) -> High Net Worth
A455: 454 | B455: 7 | C455: 9662.82 | E455: =B455*C455*D455 -> 0 | F455: =VLOOKUP('1.CLV CalcuLation'!A455,Customer_Demographic__2[],8,FALSE) -> Health | G455: =VLOOKUP(A455,Customer_Demographic__2[#All],9,FALSE) -> Affluent Customer
A456: 455 | B456: 3 | C456: 4076.17 | D456: 5 | E456: =B456*C456*D456 -> 61142.55 | F456: =VLOOKUP('1.CLV CalcuLation'!A456,Customer_Demographic__2[],8,FALSE) -> Manufacturing | G456: =VLOOKUP(A456,Customer_Demographic__2[#All],9,FALSE) -> Mass Customer
A457: 456 | B457: 5 | C457: 6261.64 | D457: 17 | E457: =B457*C457*D457 -> 532239.4 | F457: =VLOOKUP('1.CLV CalcuLation'!A457,Customer_Demographic__2[],8,FALSE) -> Manufacturing | G457: =VLOOKUP(A457,Customer_Demographic__2[#All],9,FALSE) -> Affluent Customer
A458: 457 | B458: 5 | C458: 6553.52 | D458: 17 | E458: =B458*C458*D458 -> 557049.2 | F458: =VLOOKUP('1.CLV CalcuLation'!A458,Customer_Demographic__2[],8,FALSE) -> Financial Services | G458: =VLOOKUP(A458,Customer_Demographic__2[#All],9,FALSE) -> High Net Worth
A459: 458 | B459: 5 | C459: 3615.63 | D459: 18 | E459: =B459*C459*D459 -> 325406.7 | F459: =VLOOKUP('1.CLV CalcuLation'!A459,Customer_Demographic__2[],8,FALSE) -> Manufacturing | G459: =VLOOKUP(A459,Customer_Demographic__2[#All],9,FALSE) -> Affluent Customer
A460: 459 | B460: 5 | C460: 6449.13 | D460: 13 | E460: =B460*C460*D460 -> 419193.45 | F460: =VLOOKUP('1.CLV CalcuLation'!A460,Customer_Demographic__2[],8,FALSE) -> Manufacturing | G460: =VLOOKUP(A460,Customer_Demographic__2[#All],9,FALSE) -> Mass Customer
A461: 460 | B461: 3 | C461: 3597.96 | D461: 16 | E461: =B461*C461*D461 -> 172702.08 | F461: =VLOOKUP('1.CLV CalcuLation'!A461,Customer_Demographic__2[],8,FALSE) -> Manufacturing | G461: =VLOOKUP(A461,Customer_Demographic__2[#All],9,FALSE) -> Affluent Customer
A462: 461 | B462: 8 | C462: 10366.86 | D462: 14 | E462: =B462*C462*D462 -> 1161088.3 | F462: =VLOOKUP('1.CLV CalcuLation'!A462,Customer_Demographic__2[],8,FALSE) -> Health | G462: =VLOOKUP(A462,Customer_Demographic__2[#All],9,FALSE) -> Mass Customer
A463: 462 | B463: 6 | C463: 7830.79 | D463: 5 | E463: =B463*C463*D463 -> 234923.7 | F463: =VLOOKUP('1.CLV CalcuLation'!A463,Customer_Demographic__2[],8,FALSE) -> Manufacturing | G463: =VLOOKUP(A463,Customer_Demographic__2[#All],9,FALSE) -> Affluent Customer
A464: 463 | B464: 7 | C464: 7679.47 | D464: 20 | E464: =B464*C464*D464 -> 1075125.8 | F464: =VLOOKUP('1.CLV CalcuLation'!A464,Customer_Demographic__2[],8,FALSE) -> Financial Services | G464: =VLOOKUP(A464,Customer_Demographic__2[#All],9,FALSE) -> Mass Customer
A465: 464 | B465: 6 | C465: 8289.86 | D465: 10 | E465: =B465*C465*D465 -> 497391.6 | F465: =VLOOKUP('1.CLV CalcuLation'!A465,Customer_Demographic__2[],8,FALSE) -> Others | G465: =VLOOKUP(A465,Customer_Demographic__2[#All],9,FALSE) -> Mass Customer
A466: 465 | B466: 6 | C466: 4766.91 | D466: 14 | E466: =B466*C466*D466 -> 400420.44 | F466: =VLOOKUP('1.CLV CalcuLation'!A466,Customer_Demographic__2[],8,FALSE) -> Financial Services | G466: =VLOOKUP(A466,Customer_Demographic__2[#All],9,FALSE) -> Affluent Customer
A467: 466 | B467: 7 | C467: 6597.52 | D467: 2 | E467: =B467*C467*D467 -> 92365.28 | F467: =VLOOKUP('1.CLV CalcuLation'!A467,Customer_Demographic__2[],8,FALSE) -> Manufacturing | G467: =VLOOKUP(A467,Customer_Demographic__2[#All],9,FALSE) -> Affluent Customer
... A480: 479 | B480: 9 | C480: 8781.24 | D480: 4 | E480: =B480*C480*D480 -> 316124.64 | F480: =VLOOKUP('1.CLV CalcuLation'!A480,Customer_Demographic__2[],8,FALSE) -> IT | G480: =VLOOKUP(A480,Customer_Demographic__2[#All],9,FALSE) -> Mass Customer
A481: 480 | B481: 2 | C481: 3179.31 | E481: =B481*C481*D481 -> 0 | F481: =VLOOKUP('1.CLV CalcuLation'!A481,Customer_Demographic__2[],8,FALSE) -> Health | G481: =VLOOKUP(A481,Customer_Demographic__2[#All],9,FALSE) -> Mass Customer
A482: 481 | B482: 2 | C482: 2156.44 | D482: 8 | E482: =B482*C482*D482 -> 34503.04 | F482: =VLOOKUP('1.CLV CalcuLation'!A482,Customer_Demographic__2[],8,FALSE) -> Argiculture | G482: =VLOOKUP(A482,Customer_Demographic__2[#All],9,FALSE) -> Mass Customer
A483: 482 | B483: 10 | C483: 11870.13 | D483: 20 | E483: =B483*C483*D483 -> 2374026 | F483: =VLOOKUP('1.CLV CalcuLation'!A483,Customer_Demographic__2[],8,FALSE) -> Health | G483: =VLOOKUP(A483,Customer_Demographic__2[#All],9,FALSE) -> Mass Customer
A484: 483 | B484: 7 | C484: 8372.11 | D484: 9 | E484: =B484*C484*D484 -> 527442.93 | F484: =VLOOKUP('1.CLV CalcuLation'!A484,Customer_Demographic__2[],8,FALSE) -> Retail | G484: =VLOOKUP(A484,Customer_Demographic__2[#All],9,FALSE) -> Affluent Customer
A485: 484 | B485: 5 | C485: 5694.35 | D485: 22 | E485: =B485*C485*D485 -> 626378.5 | F485: =VLOOKUP('1.CLV CalcuLation'!A485,Customer_Demographic__2[],8,FALSE) -> Manufacturing | G485: =VLOOKUP(A485,Customer_Demographic__2[#All],9,FALSE) -> Mass Customer
A486: 485 | B486: 6 | C486: 5662.31 | D486: 20 | E486: =B486*C486*D486 -> 679477.2 | F486: =VLOOKUP('1.CLV CalcuLation'!A486,Customer_Demographic__2[],8,FALSE) -> Manufacturing | G486: =VLOOKUP(A486,Customer_Demographic__2[#All],9,FALSE) -> High Net Worth
A487: 486 | B487: 5 | C487: 7323.58 | D487: 15 | E487: =B487*C487*D487 -> 549268.5 | F487: =VLOOKUP('1.CLV CalcuLation'!A487,Customer_Demographic__2[],8,FALSE) -> Manufacturing | G487: =VLOOKUP(A487,Customer_Demographic__2[#All],9,FALSE) -> Affluent Customer
A488: 487 | B488: 2 | C488: 1875.15 | D488: 10 | E488: =B488*C488*D488 -> 37503 | F488: =VLOOKUP('1.CLV CalcuLation'!A488,Customer_Demographic__2[],8,FALSE) -> Health | G488: =VLOOKUP(A488,Customer_Demographic__2[#All],9,FALSE) -> Mass Customer
A489: 488 | B489: 7 | C489: 4859.1 | D489: 10 | E489: =B489*C489*D489 -> 340137 | F489: =VLOOKUP('1.CLV CalcuLation'!A489,Customer_Demographic__2[],8,FALSE) -> Property | G489: =VLOOKUP(A489,Customer_Demographic__2[#All],9,FALSE) -> Mass Customer
A490: 489 | B490: 5 | C490: 5450.69 | D490: 4 | E490: =B490*C490*D490 -> 109013.8 | F490: =VLOOKUP('1.CLV CalcuLation'!A490,Customer_Demographic__2[],8,FALSE) -> Retail | G490: =VLOOKUP(A490,Customer_Demographic__2[#All],9,FALSE) -> Mass Customer
A491: 490 | B491: 9 | C491: 9886.75 | D491: 6 | E491: =B491*C491*D491 -> 533884.5 | F491: =VLOOKUP('1.CLV CalcuLation'!A491,Customer_Demographic__2[],8,FALSE) -> Argiculture | G491: =VLOOKUP(A491,Customer_Demographic__2[#All],9,FALSE) -> Mass Customer
A492: 491 | B492: 7 | C492: 6140.67 | D492: 19 | E492: =B492*C492*D492 -> 816709.11 | F492: =VLOOKUP('1.CLV CalcuLation'!A492,Customer_Demographic__2[],8,FALSE) -> Property | G492: =VLOOKUP(A492,Customer_Demographic__2[#All],9,FALSE) -> Affluent Customer
A493: 492 | B493: 4 | C493: 5248.15 | D493: 21 | E493: =B493*C493*D493 -> 440844.6 | F493: =VLOOKUP('1.CLV CalcuLation'!A493,Customer_Demographic__2[],8,FALSE) -> Financial Services | G493: =VLOOKUP(A493,Customer_Demographic__2[#All],9,FALSE) -> Mass Customer
...

Sheet 2.SEGMENT CLV ANALYSIS
A3: JOB INDUSRY | B3: Average of CLV
A4: Argiculture | B4: 408680.22
A5: Entertainment | B5: 475657.46
A6: Financial Services | B6: 407181.76
A7: Health | B7: 450292.99
A8: IT | B8: 294016.79
A9: Manufacturing | B9: 413403
A10: Others | B10: 407028.19
A11: Property | B11: 455789.14
A12: Retail | B12: 438432.52
A13: Telecommunications | B13: 467514.08
A22: Average CLV by Wealth_segment.
A25: WEALTH SEGMENT | B25: Average of CLV
A26: Affluent Customer | B26: 407290.27
A27: High Net Worth | B27: 422150.53
A28: Mass Customer | B28: 421746.78
A30: https://drive.google.com/file/d/11NQURvgi4zJizwh10H34IeSEk6Zaxt0W/view?usp=sharing

Sheet Customer_Demographic_2
A1: customer_id | B1: first_name | C1: last_name | D1: gender | E1: past_3_years_bike_related_purchases | F1: DOB | G1: job_title | H1: job_industry_category | I1: wealth_segment | J1: deceased_indicator | K1: owns_car | L1: tenure
A2: 1 | B2: Laraine | C2: Medendorp | D2: F | E2: 93 | F2: 19644 | G2: Executive Secretary | H2: Health | I2: Mass Customer | J2: N | K2: Yes | L2: 11
A3: 2 | B3: Eli | C3: Bockman | D3: Male | E3: 81 | F3: 29571 | G3: Administrative Officer | H3: Financial Services | I3: Mass Customer | J3: N | K3: Yes | L3: 16
A4: 3 | B4: Arlin | C4: Dearle | D4: Male | E4: 61 | F4: 19744 | G4: Recruiting Manager | H4: Property | I4: Mass Customer | J4: N | K4: Yes | L4: 15
A5: 4 | B5: Talbot | D5: Male | E5: 33 | F5: 22557 | G5: Others | H5: IT | I5: Mass Customer | J5: N | K5: No | L5: 7
A6: 5 | B6: Sheila-kathryn | C6: Calton | D6: Female | E6: 56 | F6: 28258 | G6: Senior Editor | H6: Others | I6: Affluent Customer | J6: N | K6: Yes | L6: 8
A7: 6 | B7: Curr | C7: Duckhouse | D7: Male | E7: 35 | F7: 24366 | G7: Others | H7: Retail | I7: High Net Worth | J7: N | K7: Yes | L7: 13
A8: 7 | B8: Fina | C8: Merali | D8: Female | E8: 6 | F8: 27813 | G8: Others | H8: Financial Services | I8: Affluent Customer | J8: N | K8: Yes | L8: 11
A9: 8 | B9: Rod | C9: Inder | D9: Male | E9: 31 | F9: 22735 | G9: Media Manager I | H9: Others | I9: Mass Customer | J9: N | K9: No | L9: 7
A10: 9 | B10: Mala | C10: Lind | D10: Female | E10: 97 | F10: 26733 | G10: Business Systems Development Analyst | H10: Argiculture | I10: Affluent Customer | J10: N | K10: Yes | L10: 8
A11: 10 | B11: Fiorenze | C11: Birdall | D11: Female | E11: 49 | F11: 32427 | G11: Senior Quality Engineer | H11: Financial Services | I11: Mass Customer | J11: N | K11: Yes | L11: 20
A12: 11 | B12: Uriah | C12: Bisatt | D12: Male | E12: 99 | F12: 19844 | G12: Others | H12: Property | I12: Mass Customer | J12: N | K12: No | L12: 9
A13: 12 | B13: Sawyere | C13: Flattman | D13: Male | E13: 58 | F13: 34536 | G13: Nuclear Power Engineer | H13: Manufacturing | I13: Mass Customer | J13: N | K13: No | L13: 8
A14: 13 | B14: Gabriele | C14: Norcross | D14: Male | E14: 38 | F14: 20135 | G14: Developer I | H14: Financial Services | I14: High Net Worth | J14: N | K14: Yes | L14: 8
A15: 14 | B15: Rayshell | C15: Kitteman | D15: Female | E15: 85 | F15: 30400 | G15: Account Executive | H15: Financial Services | I15: Affluent Customer | J15: N | K15: No | L15: 6
A16: 15 | B16: Erroll | C16: Radage | D16: Male | E16: 91 | F16: 36720 | G16: Junior Executive | H16: Manufacturing | I16: Mass Customer | J16: N | K16: No | L16: 1
A17: 16 | B17: Harlin | C17: Parr | D17: Male | E17: 38 | F17: 28183 | G17: Media Manager IV | H17: Others | I17: Mass Customer | J17: N | K17: Yes | L17: 18
... A67: 66 | B67: Anselm | C67: Gawne | D67: Male | E67: 46 | F67: 37326 | G67: Account Executive | H67: Argiculture | I67: High Net Worth | J67: N | K67: No | L67: 1
A68: 67 | B68: Vernon | D68: Male | E68: 67 | F68: 22081 | G68: Web Developer II | H68: Retail | I68: Mass Customer | J68: N | K68: No | L68: 18
A69: 68 | B69: Dahlia | C69: Eddoes | D69: Female | E69: 37 | F69: 27140 | G69: Information Systems Manager | H69: Others | I69: Affluent Customer | J69: N | K69: No | L69: 9
A70: 69 | B70: Heidi | C70: Milner | D70: Female | E70: 16 | F70: 25376 | G70: Web Developer II | H70: Others | I70: Mass Customer | J70: N | K70: No | L70: 6
A71: 70 | B71: Foster | C71: Vannoort | D71: Male | E71: 78 | F71: 34027 | G71: Paralegal | H71: Financial Services | I71: Affluent Customer | J71: N | K71: No | L71: 8
A72: 71 | B72: Hoyt | C72: Glavias | D72: Male | E72: 30 | F72: 31074 | G72: Research Associate | H72: Argiculture | I72: Affluent Customer | J72: N | K72: Yes | L72: 12
A73: 72 | B73: Sammy | C73: Cheese | D73: Male | E73: 93 | F73: 26342 | G73: Administrative Officer | H73: Manufacturing | I73: Affluent Customer | J73: N | K73: Yes | L73: 16
A74: 73 | B74: Minette | C74: Worters | D74: Female | E74: 16 | F74: 22063 | G74: Teacher | H74: Others | I74: Affluent Customer | J74: N | K74: Yes | L74: 5
A75: 74 | B75: Pansy | C75: Kiddie | D75: Female | E75: 94 | F75: 25373 | G75: Others | H75: Others | I75: Mass Customer | J75: N | K75: Yes | L75: 6
A76: 75 | B76: Dollie | C76: Sealy | D76: Female | E76: 28 | F76: 28686 | G76: VP Product Management | H76: Property | I76: Mass Customer | J76: N | K76: No | L76: 19
A77: 76 | B77: Rea | C77: Hasser | D77: Female | E77: 20 | F77: 28513 | G77: Statistician II | H77: Retail | I77: High Net Worth | J77: N | K77: Yes | L77: 18
A78: 77 | B78: Shermie | C78: Andrin | D78: Male | E78: 79 | F78: 32763 | G78: Automation Specialist IV | H78: Financial Services | I78: Mass Customer | J78: N | K78: No | L78: 7
A79: 78 | B79: Arch | C79: Van der Kruis | D79: Male | E79: 37 | F79: 31118 | G79: Business Systems Development Analyst | H79: Argiculture | I79: Affluent Customer | J79: N | K79: No | L79: 8
A80: 79 | B80: Tybi | C80: Silliman | D80: Female | E80: 76 | F80: 25113 | G80: Account Executive | H80: Manufacturing | I80: Mass Customer | J80: N | K80: No | L80: 18
... A106: 105 | B106: Maribeth | C106: Pristnor | D106: Female | E106: 25 | F106: 37151 | G106: Recruiting Manager | H106: Manufacturing | I106: Mass Customer | J106: N | K106: No | L106: 1
A107: 106 | B107: Glyn | D107: Male | E107: 54 | F107: 24291 | G107: Software Test Engineer III | H107: Health | I107: High Net Worth | J107: N | K107: Yes | L107: 18
A108: 107 | B108: Pris | C108: Stallebrass | D108: Female | E108: 97 | F108: 33055 | G108: Nurse Practicioner | H108: Financial Services | I108: Mass Customer | J108: N | K108: Yes | L108: 9
A109: 108 | B109: Kayle | C109: Mingaud | D109: Female | E109: 4 | F109: 34407 | G109: Others | H109: Others | I109: High Net Worth | J109: N | K109: No | L109: 3
A110: 109 | B110: Cody | C110: Blabey | D110: Male | E110: 16 | F110: 28835 | G110: Marketing Assistant | H110: Others | I110: Affluent Customer | J110: N | K110: Yes | L110: 4
A111: 110 | B111: Sascha | C111: St. Quintin | D111: Male | E111: 23 | F111: 36738 | G111: Others | H111: Financial Services | I111: Affluent Customer | J111: N | K111: No | L111: 1
A112: 111 | B112: Cele | C112: Evason | D112: Female | E112: 65 | F112: 34210 | G112: Analyst Programmer | H112: Others | I112: Mass Customer | J112: N | K112: No | L112: 2
A113: 112 | B113: Shena | C113: Parren | D113: Female | E113: 88 | F113: 27618 | G113: Marketing Manager | H113: Retail | I113: High Net Worth | J113: N | K113: No | L113: 12
A114: 113 | B114: Gage | C114: Nickless | D114: Male | E114: 67 | F114: 20581 | G114: Staff Scientist | H114: Others | I114: Mass Customer | J114: N | K114: No | L114: 20
A115: 114 | B115: Sunny | C115: Swindells | D115: Female | E115: 10 | F115: 31343 | G115: Teacher | H115: Entertainment | I115: Affluent Customer | J115: N | K115: No | L115: 8
A116: 115 | B116: Alberik | C116: Mereweather | D116: Male | E116: 77 | F116: 29941 | G116: Account Executive | H116: Health | I116: Mass Customer | J116: N | K116: No | L116: 18
A117: 116 | B117: Scottie | C117: Swiffen | D117: Male | E117: 49 | F117: 36196 | G117: Assistant Professor | H117: Manufacturing | I117: Affluent Customer | J117: N | K117: Yes | L117: 2
A118: 117 | B118: Nance | C118: Suttling | D118: Female | E118: 75 | F118: 30005 | G118: Marketing Manager | H118: Manufacturing | I118: Mass Customer | J118: N | K118: No | L118: 15
A119: 118 | B119: Prentice | C119: Pearmain | D119: Male | E119: 43 | F119: 21866 | G119: Budget/Accounting Analyst IV | H119: Others | I119: High Net Worth | J119: N | K119: No | L119: 19
... A139: 138 | B139: Onofredo | C139: Franc | D139: Male | E139: 5 | F139: 31165 | G139: Recruiter | H139: Financial Services | I139: Affluent Customer | J139: N | K139: Yes | L139: 13
A140: 139 | B140: Gar | D140: Male | E140: 1 | F140: 23586 | G140: Operator | H140: Telecommunications | I140: Affluent Customer | J140: N | K140: No | L140: 4
A141: 140 | B141: Morrie | C141: Flaxon | D141: Male | E141: 9 | F141: 34474 | G141: Programmer Analyst III | H141: Manufacturing | I141: Mass Customer | J141: N | K141: No | L141: 2
A142: 141 | B142: Townsend | C142: Trobe | D142: Male | E142: 67 | F142: 19900 | G142: Teacher | H142: Financial Services | I142: High Net Worth | J142: N | K142: Yes | L142: 10
A143: 142 | B143: Bentley | C143: Fortesquieu | D143: Male | E143: 57 | F143: 24691 | G143: Quality Engineer | H143: Health | I143: Affluent Customer | J143: N | K143: No | L143: 17
A144: 143 | B144: Kendall | C144: Figg | D144: Male | E144: 19 | F144: 21064 | G144: Operator | H144: Argiculture | I144: Mass Customer | J144: N | K144: Yes | L144: 11
A145: 144 | B145: Jory | C145: Barrabeale | D145: U | E145: 71 | G145: Environmental Tech | H145: IT | I145: Mass Customer | J145: N | K145: No
A146: 145 | B146: Filippo | C146: Ferrara | D146: Male | E146: 33 | F146: 35632 | G146: Account Executive | H146: Financial Services | I146: Mass Customer | J146: N | K146: No | L146: 4
A147: 146 | B147: Ricoriki | C147: Matlock | D147: Male | E147: 34 | F147: 31145 | G147: Quality Control Specialist | H147: Manufacturing | I147: Mass Customer | J147: N | K147: No | L147: 8
A148: 147 | B148: Rea | C148: Pattrick | D148: Female | E148: 32 | F148: 27004 | G148: Analog Circuit Design manager | H148: Health | I148: Mass Customer | J148: N | K148: Yes | L148: 10
A149: 148 | B149: Jaquith | C149: Maffey | D149: Female | E149: 69 | F149: 29714 | G149: Programmer Analyst III | H149: Others | I149: Mass Customer | J149: N | K149: Yes | L149: 5
A150: 149 | B150: Drucy | C150: Kausche | D150: Female | E150: 41 | F150: 34730 | G150: Research Nurse | H150: Health | I150: Mass Customer | J150: N | K150: Yes | L150: 1
A151: 150 | B151: Bradly | C151: Crosse | D151: Male | E151: 6 | F151: 30551 | G151: Cost Accountant | H151: Financial Services | I151: Affluent Customer | J151: N | K151: No | L151: 17
A152: 151 | B152: Donnie | C152: Brimson | D152: Male | E152: 36 | F152: 23773 | G152: Marketing Manager | H152: Manufacturing | I152: Mass Customer | J152: N | K152: Yes | L152: 13
A153: 152 | B153: Stephana | C153: Cardew | D153: Female | E153: 5 | F153: 29648 | G153: Compensation Analyst | H153: Financial Services | I153: Mass Customer | J153: N | K153: No | L153: 16
A154: 153 | B154: Lorilyn | C154: Walshe | D154: Female | E154: 73 | F154: 28334 | G154: Assistant Media Planner | H154: Entertainment | I154: Mass Customer | J154: N | K154: Yes | L154: 12
A155: 154 | B155: Faydra | C155: Dulieu | D155: Female | E155: 90 | F155: 21229 | G155: Junior Executive | H155: Others | I155: Mass Customer | J155: N | K155: No | L155: 11
A156: 155 | B156: Orran | C156: Bogges | D156: Male | E156: 4 | F156: 31409 | G156: Quality Engineer | H156: Manufacturing | I156: Mass Customer | J156: N | K156: No | L156: 10
A157: 156 | B157: Shayla | C157: Rimmington | D157: Female | E157: 23 | F157: 29107 | G157: Cost Accountant | H157: Financial Services | I157: Mass Customer | J157: N | K157: Yes | L157: 11
... A168: 167 | B168: Nathalie | C168: Tideswell | D168: Female | E168: 95 | F168: 25503 | G168: Others | H168: Health | I168: High Net Worth | J168: N | K168: Yes | L168: 17
A169: 168 | B169: Reggie | C169: Broggetti | D169: U | E169: 8 | G169: General Manager | H169: IT | I169: Affluent Customer | J169: N | K169: Yes
A170: 169 | B170: Alfy | C170: Bruhnke | D170: Male | E170: 20 | F170: 21112 | G170: Data Coordiator | H170: Telecommunications | I170: High Net Worth | J170: N | K170: Yes | L170: 5
A171: 170 | B171: Jammal | C171: Gever | D171: Male | E171: 80 | F171: 27547 | G171: Pharmacist | H171: Health | I171: High Net Worth | J171: N | K171: No | L171: 21
A172: 171 | B172: Halli | C172: Davidoff | D172: Female | E172: 62 | F172: 25906 | G172: Assistant Manager | H172: Manufacturing | I172: Mass Customer | J172: N | K172: No | L172: 10
A173: 172 | B173: Hilton | C173: Carney | D173: Male | E173: 54 | F173: 32398 | G173: Editor | H173: Manufacturing | I173: Affluent Customer | J173: N | K173: Yes | L173: 6
A174: 173 | B174: Ebba | C174: Hanselmann | D174: Female | E174: 99 | F174: 35432 | G174: General Manager | H174: Health | I174: Affluent Customer | J174: N | K174: No | L174: 1
A175: 174 | B175: Catie | C175: Tosspell | D175: Female | E175: 93 | F175: 32838 | G175: Food Chemist | H175: Health | I175: Mass Customer | J175: N | K175: No | L175: 12
A176: 175 | B176: Templeton | C176: Hambrook | D176: Male | E176: 36 | F176: 27726 | G176: Quality Engineer | H176: Manufacturing | I176: Affluent Customer | J176: N | K176: No | L176: 5
A177: 176 | B177: Angelo | C177: Clayal | D177: Male | E177: 39 | F177: 33707 | G177: Accountant I | H177: Property | I177: Mass Customer | J177: N | K177: No | L177: 10
A178: 177 | B178: Ondrea | C178: Pablos | D178: Female | E178: 25 | F178: 32821 | G178: Professor | H178: Financial Services | I178: High Net Worth | J178: N | K178: No | L178: 4
A179: 178 | B179: Matthieu | C179: Bertelmot | D179: Male | E179: 2 | F179: 24565 | G179: Others | H179: Others | I179: Affluent Customer | J179: N | K179: No | L179: 8
A180: 179 | B180: Esteban | C180: Sewill | D180: Male | E180: 23 | F180: 24238 | G180: Environmental Tech | H180: Manufacturing | I180: High Net Worth | J180: N | K180: Yes | L180: 6
A181: 180 | B181: Trisha | C181: Neasham | D181: Female | E181: 16 | F181: 26193 | G181: Web Designer III | H181: Argiculture | I181: Affluent Customer | J181: N | K181: No | L181: 14
... A197: 196 | B197: Swen | C197: Odhams | D197: Male | E197: 90 | F197: 24160 | G197: Programmer Analyst II | H197: Manufacturing | I197: High Net Worth | J197: N | K197: No | L197: 6
A198: 197 | B198: Avis | D198: Female | E198: 32 | F198: 28152 | G198: Others | H198: Others | I198: High Net Worth | J198: N | K198: No | L198: 5
A199: 198 | B199: Vanya | C199: Gumb | D199: Female | E199: 82 | F199: 29919 | G199: Assistant Media Planner | H199: Entertainment | I199: Mass Customer | J199: N | K199: No | L199: 16
A200: 199 | B200: Verla | C200: Alven | D200: Female | E200: 61 | F200: 28534 | G200: Junior Executive | H200: Health | I200: Mass Customer | J200: N | K200: Yes | L200: 21
A201: 200 | B201: Hube | C201: Weald | D201: Male | E201: 7 | F201: 20855 | G201: Physical Therapy Assistant | H201: Property | I201: Affluent Customer | J201: N | K201: Yes | L201: 19
A202: 201 | B202: Salem | C202: Huie | D202: Male | E202: 45 | F202: 24217 | G202: Design Engineer | H202: Manufacturing | I202: Mass Customer | J202: N | K202: Yes | L202: 11
A203: 202 | B203: Audie | C203: Pillinger | D203: Female | E203: 38 | F203: 23186 | G203: Librarian | H203: Entertainment | I203: Affluent Customer | J203: N | K203: Yes | L203: 16
A204: 203 | B204: Donovan | C204: Conry | D204: Male | E204: 71 | F204: 23389 | G204: Senior Quality Engineer | H204: Argiculture | I204: Mass Customer | J204: N | K204: Yes | L204: 11
A205: 204 | B205: Thorny | C205: Hackworth | D205: Male | E205: 56 | F205: 28034 | G205: Editor | H205: Financial Services | I205: Mass Customer | J205: N | K205: No | L205: 5
A206: 205 | B206: Rolfe | C206: Kellard | D206: Male | E206: 18 | F206: 21520 | G206: Administrative Assistant II | H206: Financial Services | I206: Mass Customer | J206: N | K206: Yes | L206: 6
A207: 206 | B207: Mari | C207: Chevolleau | D207: Female | E207: 98 | F207: 19924 | G207: Statistician I | H207: Others | I207: Mass Customer | J207: N | K207: Yes | L207: 14
A208: 207 | B208: Adena | C208: Whyman | D208: Female | E208: 9 | F208: 34556 | G208: Others | H208: Others | I208: Mass Customer | J208: N | K208: No | L208: 7
A209: 208 | B209: Rutter | C209: Excell | D209: Male | E209: 57 | F209: 34638 | G209: Office Assistant III | H209: Property | I209: High Net Worth | J209: N | K209: No | L209: 5
A210: 209 | B210: Udall | C210: Bellard | D210: Male | E210: 9 | F210: 21060 | G210: Analog Circuit Design manager | H210: Others | I210: Affluent Customer | J210: N | K210: Yes | L210: 6
A211: 210 | B211: Albrecht | C211: Thomasson | D211: Male | E211: 50 | F211: 23333 | G211: Assistant Manager | H211: Property | I211: Mass Customer | J211: N | K211: No | L211: 18
A212: 211 | B212: Beitris | D212: Female | E212: 6 | F212: 27092 | G212: VP Marketing | H212: Manufacturing | I212: Mass Customer | J212: N | K212: Yes | L212: 5
A213: 212 | B213: Nanice | C213: Ellse | D213: Female | E213: 21 | F213: 37214 | G213: Desktop Support Technician | H213: IT | I213: Affluent Customer | J213: N | K213: No | L213: 1
A214: 213 | B214: Lockwood | C214: Exroll | D214: Male | E214: 13 | F214: 35199 | G214: Actuary | H214: Financial Services | I214: High Net Worth | J214: N | K214: Yes | L214: 6
A215: 214 | B215: Jeramie | C215: Cellier | D215: Male | E215: 82 | F215: 21153 | G215: Food Chemist | H215: Health | I215: Mass Customer | J215: N | K215: No | L215: 6
A216: 215 | B216: Debera | C216: Foxworthy | D216: Female | E216: 37 | F216: 27204 | G216: Assistant Professor | H216: Retail | I216: High Net Worth | J216: N | K216: Yes | L216: 18
A217: 216 | B217: Cinderella | C217: Parcall | D217: Female | E217: 12 | F217: 34711 | G217: Quality Engineer | H217: Financial Services | I217: High Net Worth | J217: N | K217: Yes | L217: 7
A218: 217 | B218: Jeralee | C218: Quartly | D218: Female | E218: 63 | F218: 29198 | G218: Others | H218: Manufacturing | I218: High Net Worth | J218: N | K218: No | L218: 16
...
